autodict/__init__.py
autodict/implementation.py
autodict/version.py
autodict/json_drivers/__init__.py
autodict/json_drivers/base.py
autodict/json_drivers/orjson.py
autodict/json_drivers/rapidjson.py
autodict/json_drivers/simplejson.py
autodict/json_drivers/ujson.py
tests/__init__.py
tests/__main__.py
tests/base.py
tests/test_autodict.py
tests/json_drivers/__init__.py
tests/json_drivers/test_base.py
tests/json_drivers/test_orjson.py
tests/json_drivers/test_rapidjson.py
tests/json_drivers/test_simplejson.py
tests/json_drivers/test_ujson.py
AutoDict-2.0.0.dist-info/LICENSE
AutoDict-2.0.0.dist-info/METADATA
AutoDict-2.0.0.dist-info/WHEEL
AutoDict-2.0.0.dist-info/top_level.txt
AutoDict-2.0.0.dist-info/RECORD
