Metadata-Version: 2.1
Name: AutoDict
Version: 2.0.0
Summary: Dictionary that automatically adds children dictionaries as necessary
Home-page: https://github.com/WattsUp/AutoDict
Author: Bradley Davis
Author-email: me@bradleydavis.tech
License: MIT
Classifier: Programming Language :: Python :: 3
Classifier: Operating System :: OS Independent
Classifier: Development Status :: 4 - Beta
Classifier: License :: OSI Approved :: MIT License
Classifier: Intended Audience :: Developers
Classifier: Topic :: Software Development :: Libraries
Classifier: Programming Language :: Python :: 3
Classifier: Programming Language :: Python :: 3.7
Classifier: Programming Language :: Python :: 3.8
Classifier: Programming Language :: Python :: 3.9
Classifier: Programming Language :: Python :: 3.10
Requires-Python: >=3.7
License-File: LICENSE
Provides-Extra: extras
Requires-Dist: orjson ; extra == 'extras'
Requires-Dist: ujson ; extra == 'extras'
Requires-Dist: python-rapidjson ; extra == 'extras'
Requires-Dist: simplejson ; extra == 'extras'
Provides-Extra: test
Requires-Dist: coverage ; extra == 'test'
Requires-Dist: pylint ; extra == 'test'
